FlaskSQL-1.0.0-py3.12-nspkg.pth
flaskext/mysql.py
FlaskSQL-1.0.0.dist-info/LICENSE
FlaskSQL-1.0.0.dist-info/METADATA
FlaskSQL-1.0.0.dist-info/WHEEL
FlaskSQL-1.0.0.dist-info/namespace_packages.txt
FlaskSQL-1.0.0.dist-info/top_level.txt
FlaskSQL-1.0.0.dist-info/RECORD
