Metadata-Version: 2.1
Name: FlaskSQL
Version: 1.0.0
Summary: MySQL integration for Flask
Home-page: https://github.com/jzhong00/FlaskSQL/
Author: Jason Zhong
Author-email: jasonyzhong06@gmail.com
License: MIT
Platform: any
Classifier: Environment :: Web Environment
Classifier: Intended Audience :: Developers
Classifier: License :: OSI Approved :: MIT License
Classifier: Operating System :: OS Independent
Classifier: Programming Language :: Python
Classifier: Topic :: Internet :: WWW/HTTP :: Dynamic Content
Classifier: Topic :: Software Development :: Libraries :: Python Modules
License-File: LICENSE
Requires-Dist: Flask
Requires-Dist: PyMySQL
